{
  "mission": "Centralize Workflow Stage Definitions",
  "mission_path": "docs/concert/missions/2026-03-29-centralize-workflow-stages",
  "workflow": "mission-medium",
  "workflow_path": "docs/concert/workflows/CONCERT-WORKFLOW-MISSION-MEDIUM.md",
  "branch": "concert/centralize-workflow-stages",
  "pr_number": 0,
  "status_display": "wip_pr",
  "feature_size": "medium",
  "stage": "vision",
  "pipeline": {
    "vision": "draft"
  },
  "phases_completed": 0,
  "phases_total": 0,
  "tasks_completed": 0,
  "tasks_total": 0,
  "commits": 0,
  "cost": {
    "estimated_remaining": "",
    "spent_this_mission": "",
    "by_stage": {}
  },
  "blockers": [],
  "telemetry": [],
  "failure_log": [],
  "history": [
    {
      "action": "mission_initialized",
      "timestamp": "2026-03-29T17:45:00Z",
      "details": "Medium mission — centralize workflow stage definitions and user guidance"
    }
  ],
  "next_steps": [
    "Review vision: /concert:review",
    "Accept vision: /concert:accept"
  ]
}
